timelength/__init__.py
timelength/dataclasses.py
timelength/enums.py
timelength/errors.py
timelength/locales/english.json
timelength/locales/spanish.json
timelength/locales.py
timelength/parsers/common.py
timelength/parsers/parser_one.py
timelength/timelength.py
timelength-3.0.2.dist-info/LICENSE
timelength-3.0.2.dist-info/METADATA
timelength-3.0.2.dist-info/WHEEL
timelength-3.0.2.dist-info/RECORD
