Metadata-Version: 2.3
Name: timelength
Version: 3.0.2
Summary: A flexible python duration parser designed for human readable lengths of time.
License: MIT
Keywords: timelength,duration,parser,parsing,time,datetime,timedelta
Author: Etorix
Author-email: admin@etorix.dev
Requires-Python: >=3.9,<4.0
Classifier: License :: OSI Approved :: MIT License
Classifier: Programming Language :: Python :: 3
Classifier: Programming Language :: Python :: 3.9
Classifier: Programming Language :: Python :: 3.10
Classifier: Programming Language :: Python :: 3.11
Classifier: Programming Language :: Python :: 3.12
Classifier: Programming Language :: Python :: 3.13
Project-URL: Homepage, https://pypi.org/project/timelength/
Project-URL: Repository, https://github.com/EtorixDev/timelength/
